[
    {
        "model": "doctors.doctor",
        "pk": 1,
        "fields": {
            "name": "Dr. Hesham Negm",
            "specialty": "Psychologist",
            "language": "English",
            "rating": 4.7,
            "reviews_count": 120,
            "joined_months_ago": 24,
            "sessions_count": 350,
            "price_60_min": 400,
            "price_30_min": 250,
            "image": "https://example.com/doc1.jpg",
            "certificates": ["PhD in Clinical Psychology", "CBT Certification"],
            "available_days": ["Sunday", "Tuesday", "Thursday"]
        }
    },
    {
        "model": "doctors.doctor",
        "pk": 2,
        "fields": {
            "name": "Dr. Doaa Hassan",
            "specialty": "Child Psychiatrist",
            "language": "Arabic, English",
            "rating": 4.9,
            "reviews_count": 200,
            "joined_months_ago": 36,
            "sessions_count": 500,
            "price_60_min": 450,
            "price_30_min": 300,
            "image": "https://example.com/doc2.jpg",
            "certificates": ["MD in Psychiatry", "Child Psychiatry Fellowship"],
            "available_days": ["Monday", "Wednesday", "Friday"]
        }
    },
    {
        "model": "doctors.doctor",
        "pk": 3,
        "fields": {
            "name": "Dr. Osama Ali",
            "specialty": "Neurologist",
            "language": "English",
            "rating": 4.6,
            "reviews_count": 90,
            "joined_months_ago": 18,
            "sessions_count": 220,
            "price_60_min": 500,
            "price_30_min": 300,
            "image": "https://example.com/doc3.jpg",
            "certificates": ["MD Neurology", "Epilepsy Specialist"],
            "available_days": ["Tuesday", "Thursday", "Saturday"]
        }
    },
    {
        "model": "doctors.doctor",
        "pk": 4,
        "fields": {
            "name": "Dr. Reham Essam",
            "specialty": "Clinical Psychologist",
            "language": "Arabic, English",
            "rating": 4.8,
            "reviews_count": 150,
            "joined_months_ago": 30,
            "sessions_count": 400,
            "price_60_min": 420,
            "price_30_min": 280,
            "image": "https://example.com/doc4.jpg",
            "certificates": ["MSc Clinical Psychology", "Mindfulness Training"],
            "available_days": ["Monday", "Wednesday", "Friday"]
        }
    }
    ]